SimpleSurface/DrawSurface.py
SimpleSurface/SimpleSurface.py
SimpleSurface/TextSurface.py
SimpleSurface/__init__.py
SimpleSurface/helpers.py
simplesurface-2025.8.7.dist-info/LICENSE
simplesurface-2025.8.7.dist-info/METADATA
simplesurface-2025.8.7.dist-info/WHEEL
simplesurface-2025.8.7.dist-info/top_level.txt
simplesurface-2025.8.7.dist-info/RECORD
