Metadata-Version: 2.1
Name: SimpleSurface
Version: 2025.8.7
Summary: A simpler version of Pycairo's ImageSurface
Home-page: https://github.com/dylan-bennett/simple-surface
Author: Dylan Bennett
Author-email: dylanab@gmail.com
Project-URL: Bug Tracker, https://github.com/dylan-bennett/simple-surface/issues
Classifier: Programming Language :: Python :: 3
Classifier: License :: OSI Approved :: MIT License
Classifier: Operating System :: Unix
Requires-Python: >=3.6
License-File: LICENSE
Requires-Dist: pycairo>=1.20
